rik/__init__.py
rik/consts.py
rik/funcs.py
rik/parsers.py
rik/path_constraints.py
rik/integrity/__init__.py
rik/integrity/hash.py
rik/integrity/integrity.py
rik/integrity/par2.py
rik-0.0.1.data/scripts/rik
rik-0.0.1.dist-info/LICENSE
rik-0.0.1.dist-info/METADATA
rik-0.0.1.dist-info/WHEEL
rik-0.0.1.dist-info/top_level.txt
rik-0.0.1.dist-info/RECORD
