Metadata-Version: 2.1
Name: rik
Version: 0.0.1
Summary: Recursive Integrity Keeper
Home-page: https://github.com/usert5432/rik
Author: Dmitrii Torbunov
Author-email: torbu001@alumni.umn.edu
License: BSD-2
License-File: LICENSE
